{"short_name":"D35-D35G","long_name":"Depot-35 Gate ⇔ Depot-35 Kannalli","directions":[{"direction":"UP","headsign":"Depot-35 Gate","path":[[12.972563,77.442696],[12.9726,77.44268]],"stops":[{"id":"24860","name":"Depot-35 Kannalli","lat":12.97253,"lon":77.44263,"sequence":1},{"id":"35809","name":"Depot-35 Gate","lat":12.9726,"lon":77.44268,"sequence":2}]},{"direction":"DOWN","headsign":"Depot-35 Kannalli","path":[[12.9726,77.44268],[12.972563,77.442696]],"stops":[{"id":"35809","name":"Depot-35 Gate","lat":12.9726,"lon":77.44268,"sequence":1},{"id":"24860","name":"Depot-35 Kannalli","lat":12.97253,"lon":77.44263,"sequence":2}]}]}